src/earth_view/__init__.py
src/earth_view/earth_view.py
src/earth_view/images.py
src/earth_view/main.py
earth_view_api-0.0.1.dist-info/METADATA
earth_view_api-0.0.1.dist-info/WHEEL
earth_view_api-0.0.1.dist-info/entry_points.txt
earth_view_api-0.0.1.dist-info/licenses/LICENSE.md
earth_view_api-0.0.1.dist-info/RECORD
