Metadata-Version: 2.1
Name: earth-view-api
Version: 0.0.1
Summary: Python API for downloading Google Earth View images
Project-URL: Homepage, https://github.com/jacobwhall/python-earth-view
Project-URL: Bug Tracker, https://github.com/jacobwhall/python-earth-view/issues
Author-email: Jacob Hall <email@jacobhall.net>
License: GNU General Public License
License-File: LICENSE.md
Classifier: License :: OSI Approved :: GNU General Public License v3 or later (GPLv3+)
Classifier: Programming Language :: Python :: 3
Requires-Python: >=3.5
Requires-Dist: click
Requires-Dist: requests
